<?xml version="1.0" encoding="UTF-8" standalone="yes"?>
<ns3:mets xmlns:ns2="http://www.w3.org/1999/xlink" xmlns:ns3="http://www.loc.gov/METS/" xmlns:xsi="http://www.w3.org/2001/XMLSchema-instance" OBJID="224222" LABEL="F_01-7_Broschüren-Sonderdrucke-Undat_1895-Henri-Albert-Les-Jeunes-Viennois" PROFILE="TRP_V1" xsi:schemaLocation="http://www.loc.gov/METS/ http://www.loc.gov/standards/mets/mets.xsd">
    <ns3:metsHdr CREATEDATE="2024-03-26T09:59:24.166+01:00" LASTMODDATE="2024-03-26T09:59:24.166+01:00" RECORDSTATUS="SUBMITTED">
        <ns3:agent ROLE="CREATOR" TYPE="ORGANIZATION">
            <ns3:name>UIBK</ns3:name>
            <ns3:note>This METS file was generated by Transkribus</ns3:note>
        </ns3:agent>
    </ns3:metsHdr>
    <ns3:amdSec ID="SOURCE">
        <ns3:sourceMD ID="MD_ORIG">
            <ns3:mdWrap ID="TRP_DOC_MD" MDTYPE="OTHER">
                <ns3:xmlData>
                    <trpDocMetadata>
                        <docId>224222</docId>
                        <title>F_01-7_Broschüren-Sonderdrucke-Undat_1895-Henri-Albert-Les-Jeunes-Viennois</title>
                        <uploadTimestamp>1570454163693</uploadTimestamp>
                        <uploader>martin.anton.mueller@oeaw.ac.at</uploader>
                        <uploaderId>40391</uploaderId>
                        <nrOfPages>7</nrOfPages>
                        <pageId>9515090</pageId>
                        <url>https://files.transkribus.eu/Get?fileType=view&amp;id=OQFRSSUUELGRSKCWQPHKBYPL</url>
                        <thumbUrl>https://files.transkribus.eu/Get?fileType=thumb&amp;id=OQFRSSUUELGRSKCWQPHKBYPL</thumbUrl>
                        <status>0</status>
                        <fimgStoreColl>TrpDoc_DEA_224222</fimgStoreColl>
                        <localFolder>/mnt/transkribus/export/TRP_EXPORT_6389896091856322989/224222/F_01-7_Broschüren-Sonderdrucke-Undat_1895-Henri-Albert-Les-Jeunes-Viennois</localFolder>
                        <origDocId>0</origDocId>
                        <collectionList>
                            <colList>
<colId>50217</colId>
<colName>Arthur Schnitzler – Archiv der Zeitungssauschnittte https://schnitzler-zeitungen.acdh.oeaw.ac.at</colName>
<description>created by martin.anton.mueller@oeaw.ac.at</description>
<crowdsourcing>false</crowdsourcing>
<elearning>false</elearning>
<nrOfDocuments>0</nrOfDocuments>
                            </colList>
                        </collectionList>
                        <mainColId>50217</mainColId>
                    </trpDocMetadata>
                </ns3:xmlData>
            </ns3:mdWrap>
        </ns3:sourceMD>
    </ns3:amdSec>
    <ns3:fileSec>
        <ns3:fileGrp ID="MASTER">
            <ns3:fileGrp ID="IMG">
                <ns3:file ID="IMG_1" SEQ="1" MIMETYPE="image/jpeg" CREATED="2022-09-06T12:19:51.748+02:00" CHECKSUM="c9a44730637122d20ae2de5d445f6904" CHECKSUMTYPE="MD5">
                    <ns3:FLocat LOCTYPE="OTHER" OTHERLOCTYPE="FILE" ns2:type="simple" ns2:href="224222_0001.jpeg"/>
                </ns3:file>
                <ns3:file ID="IMG_2" SEQ="2" MIMETYPE="image/jpeg" CREATED="2021-11-23T02:49:16.699+01:00" CHECKSUM="a7d1bf4e0f7426583e1d9d4f97094e5d" CHECKSUMTYPE="MD5">
                    <ns3:FLocat LOCTYPE="OTHER" OTHERLOCTYPE="FILE" ns2:type="simple" ns2:href="224222_0002.jpeg"/>
                </ns3:file>
                <ns3:file ID="IMG_3" SEQ="3" MIMETYPE="image/jpeg" CREATED="2021-09-09T17:54:30.908+02:00" CHECKSUM="08e24e961750aaf492924874ca1d0742" CHECKSUMTYPE="MD5">
                    <ns3:FLocat LOCTYPE="OTHER" OTHERLOCTYPE="FILE" ns2:type="simple" ns2:href="224222_0003.jpeg"/>
                </ns3:file>
                <ns3:file ID="IMG_4" SEQ="4" MIMETYPE="image/jpeg" CREATED="2023-05-24T10:29:49.946+02:00" CHECKSUM="0959444bc93e45c1b8f97e5ac9a9cfc8" CHECKSUMTYPE="MD5">
                    <ns3:FLocat LOCTYPE="OTHER" OTHERLOCTYPE="FILE" ns2:type="simple" ns2:href="224222_0004.jpeg"/>
                </ns3:file>
                <ns3:file ID="IMG_5" SEQ="5" MIMETYPE="image/jpeg" CREATED="2021-08-13T23:42:54.445+02:00" CHECKSUM="6bca1c72325e2d295aba390d9e1d64b1" CHECKSUMTYPE="MD5">
                    <ns3:FLocat LOCTYPE="OTHER" OTHERLOCTYPE="FILE" ns2:type="simple" ns2:href="224222_0005.jpeg"/>
                </ns3:file>
                <ns3:file ID="IMG_6" SEQ="6" MIMETYPE="image/jpeg" CREATED="2023-04-02T20:15:49.071+02:00" CHECKSUM="60f182de820d0394964e2f99837c10bb" CHECKSUMTYPE="MD5">
                    <ns3:FLocat LOCTYPE="OTHER" OTHERLOCTYPE="FILE" ns2:type="simple" ns2:href="224222_0006.jpeg"/>
                </ns3:file>
                <ns3:file ID="IMG_7" SEQ="7" MIMETYPE="image/jpeg" CREATED="2022-01-21T02:17:58.199+01:00" CHECKSUM="7760a81ba9eddf821e0dd50d1d3ccab3" CHECKSUMTYPE="MD5">
                    <ns3:FLocat LOCTYPE="OTHER" OTHERLOCTYPE="FILE" ns2:type="simple" ns2:href="224222_0007.jpeg"/>
                </ns3:file>
            </ns3:fileGrp>
            <ns3:fileGrp ID="PAGEXML">
                <ns3:file ID="PAGEXML_1" SEQ="1" MIMETYPE="application/xml" CREATED="2024-03-26T09:59:21.807+01:00" CHECKSUM="409b3e814aa642f581e3aa524c93005f" CHECKSUMTYPE="MD5">
                    <ns3:FLocat LOCTYPE="OTHER" OTHERLOCTYPE="FILE" ns2:type="simple" ns2:href="page/224222_0001.xml"/>
                </ns3:file>
                <ns3:file ID="PAGEXML_2" SEQ="2" MIMETYPE="application/xml" CREATED="2024-03-26T09:59:22.147+01:00" CHECKSUM="83ebca8f348607c62bfb52b78f7bc269" CHECKSUMTYPE="MD5">
                    <ns3:FLocat LOCTYPE="OTHER" OTHERLOCTYPE="FILE" ns2:type="simple" ns2:href="page/224222_0002.xml"/>
                </ns3:file>
                <ns3:file ID="PAGEXML_3" SEQ="3" MIMETYPE="application/xml" CREATED="2024-03-26T09:59:22.659+01:00" CHECKSUM="6dc3525dc56eb5346f5ce608048920fb" CHECKSUMTYPE="MD5">
                    <ns3:FLocat LOCTYPE="OTHER" OTHERLOCTYPE="FILE" ns2:type="simple" ns2:href="page/224222_0003.xml"/>
                </ns3:file>
                <ns3:file ID="PAGEXML_4" SEQ="4" MIMETYPE="application/xml" CREATED="2024-03-26T09:59:23.035+01:00" CHECKSUM="e93a35253187df23030c63c19bb7be9e" CHECKSUMTYPE="MD5">
                    <ns3:FLocat LOCTYPE="OTHER" OTHERLOCTYPE="FILE" ns2:type="simple" ns2:href="page/224222_0004.xml"/>
                </ns3:file>
                <ns3:file ID="PAGEXML_5" SEQ="5" MIMETYPE="application/xml" CREATED="2024-03-26T09:59:23.407+01:00" CHECKSUM="01d4ad6eb2c7773cae2a598e8805fac8" CHECKSUMTYPE="MD5">
                    <ns3:FLocat LOCTYPE="OTHER" OTHERLOCTYPE="FILE" ns2:type="simple" ns2:href="page/224222_0005.xml"/>
                </ns3:file>
                <ns3:file ID="PAGEXML_6" SEQ="6" MIMETYPE="application/xml" CREATED="2024-03-26T09:59:23.799+01:00" CHECKSUM="63c3c31f5d26a332c93410b8cb97ee1b" CHECKSUMTYPE="MD5">
                    <ns3:FLocat LOCTYPE="OTHER" OTHERLOCTYPE="FILE" ns2:type="simple" ns2:href="page/224222_0006.xml"/>
                </ns3:file>
                <ns3:file ID="PAGEXML_7" SEQ="7" MIMETYPE="application/xml" CREATED="2024-03-26T09:59:24.155+01:00" CHECKSUM="63f7b859487ded44064b5fc97ae42f6d" CHECKSUMTYPE="MD5">
                    <ns3:FLocat LOCTYPE="OTHER" OTHERLOCTYPE="FILE" ns2:type="simple" ns2:href="page/224222_0007.xml"/>
                </ns3:file>
            </ns3:fileGrp>
        </ns3:fileGrp>
    </ns3:fileSec>
    <ns3:structMap ID="TRP_STRUCTMAP" TYPE="MANUSCRIPT">
        <ns3:div ID="TRP_DOC_DIV" ADMID="MD_ORIG">
            <ns3:div ID="PAGE_1" ORDER="1" TYPE="SINGLE_PAGE">
                <ns3:fptr>
                    <ns3:area FILEID="IMG_1"/>
                </ns3:fptr>
                <ns3:fptr>
                    <ns3:area FILEID="PAGEXML_1"/>
                </ns3:fptr>
            </ns3:div>
            <ns3:div ID="PAGE_2" ORDER="2" TYPE="SINGLE_PAGE">
                <ns3:fptr>
                    <ns3:area FILEID="IMG_2"/>
                </ns3:fptr>
                <ns3:fptr>
                    <ns3:area FILEID="PAGEXML_2"/>
                </ns3:fptr>
            </ns3:div>
            <ns3:div ID="PAGE_3" ORDER="3" TYPE="SINGLE_PAGE">
                <ns3:fptr>
                    <ns3:area FILEID="IMG_3"/>
                </ns3:fptr>
                <ns3:fptr>
                    <ns3:area FILEID="PAGEXML_3"/>
                </ns3:fptr>
            </ns3:div>
            <ns3:div ID="PAGE_4" ORDER="4" TYPE="SINGLE_PAGE">
                <ns3:fptr>
                    <ns3:area FILEID="IMG_4"/>
                </ns3:fptr>
                <ns3:fptr>
                    <ns3:area FILEID="PAGEXML_4"/>
                </ns3:fptr>
            </ns3:div>
            <ns3:div ID="PAGE_5" ORDER="5" TYPE="SINGLE_PAGE">
                <ns3:fptr>
                    <ns3:area FILEID="IMG_5"/>
                </ns3:fptr>
                <ns3:fptr>
                    <ns3:area FILEID="PAGEXML_5"/>
                </ns3:fptr>
            </ns3:div>
            <ns3:div ID="PAGE_6" ORDER="6" TYPE="SINGLE_PAGE">
                <ns3:fptr>
                    <ns3:area FILEID="IMG_6"/>
                </ns3:fptr>
                <ns3:fptr>
                    <ns3:area FILEID="PAGEXML_6"/>
                </ns3:fptr>
            </ns3:div>
            <ns3:div ID="PAGE_7" ORDER="7" TYPE="SINGLE_PAGE">
                <ns3:fptr>
                    <ns3:area FILEID="IMG_7"/>
                </ns3:fptr>
                <ns3:fptr>
                    <ns3:area FILEID="PAGEXML_7"/>
                </ns3:fptr>
            </ns3:div>
        </ns3:div>
    </ns3:structMap>
</ns3:mets>
